{
  "attempts": 1,
  "columns": [
    "序号",
    "代码",
    "名称",
    "涨跌幅",
    "最新价",
    "涨停价",
    "成交额",
    "流通市值",
    "总市值",
    "换手率",
    "涨速",
    "振幅",
    "昨日封板时间",
    "昨日连板数",
    "涨停统计",
    "所属行业"
  ],
  "elapsed_seconds": 0.171,
  "failure_reason": null,
  "fetched_at": "2026-06-24T16:00:36.385032+08:00",
  "function_name": "stock_zt_pool_previous_em",
  "params": {
    "date": "20260624"
  },
  "raw_path": "/mnt/tool/2-projects/a-share-info-hub/data/raw/2026-06-24/stock_zt_pool_previous_em/response.json",
  "row_count": 96,
  "source": "akshare.stock_zt_pool_previous_em",
  "status": "success"
}
